{
  "id": 286,
  "locationId": 2,
  "date": "2025-08-29",
  "revenue": 0,
  "cardRevenue": 0,
  "workLogs": [
    {
      "hoursWorked": 9.5,
      "employeeSlug": "kacper"
    }
  ],
  "inventory": [
    {
      "productId": 1,
      "quantity": 1
    },
    {
      "productId": 2,
      "quantity": 1
    },
    {
      "productId": 61,
      "quantity": 1
    },
    {
      "productId": 10,
      "quantity": 1
    },
    {
      "productId": 4,
      "quantity": 1
    },
    {
      "productId": 5,
      "quantity": 3
    },
    {
      "productId": 17,
      "quantity": 1
    },
    {
      "productId": 6,
      "quantity": 3
    },
    {
      "productId": 39,
      "quantity": 1
    },
    {
      "productId": 7,
      "quantity": 4
    },
    {
      "productId": 8,
      "quantity": 2
    },
    {
      "productId": 13,
      "quantity": 1
    },
    {
      "productId": 35,
      "quantity": 1
    },
    {
      "productId": 29,
      "quantity": 1
    },
    {
      "productId": 16,
      "quantity": 1
    },
    {
      "productId": 38,
      "quantity": 1
    },
    {
      "productId": 12,
      "quantity": 1
    },
    {
      "productId": 19,
      "quantity": 1
    },
    {
      "productId": 54,
      "quantity": 1
    }
  ]
}