{
  "id": 397,
  "locationId": 3,
  "date": "2026-01-29",
  "revenue": 300,
  "cardRevenue": 64,
  "workLogs": [
    {
      "hoursWorked": 6.5,
      "employeeSlug": "sebastian"
    }
  ],
  "inventory": [
    {
      "productId": 1,
      "quantity": 1
    },
    {
      "productId": 2,
      "quantity": 2
    },
    {
      "productId": 3,
      "quantity": 1
    },
    {
      "productId": 21,
      "quantity": 1
    },
    {
      "productId": 64,
      "quantity": 15
    },
    {
      "productId": 8,
      "quantity": 1
    },
    {
      "productId": 16,
      "quantity": 1
    },
    {
      "productId": 65,
      "quantity": 1
    },
    {
      "productId": 18,
      "quantity": 1
    },
    {
      "productId": 12,
      "quantity": 1
    },
    {
      "productId": 67,
      "quantity": 1
    }
  ]
}